magic_notifier/__init__.py
magic_notifier/admin.py
magic_notifier/apps.py
magic_notifier/consumers.py
magic_notifier/emailer.py
magic_notifier/models.py
magic_notifier/notifier.py
magic_notifier/pusher.py
magic_notifier/serializers.py
magic_notifier/settings.py
magic_notifier/smser.py
magic_notifier/tasks.py
magic_notifier/telegramer.py
magic_notifier/utils.py
magic_notifier/views.py
magic_notifier/whatsapper.py
magic_notifier/email_clients/__init__.py
magic_notifier/email_clients/amazon_ses.py
magic_notifier/email_clients/django_email.py
magic_notifier/management/__init__.py
magic_notifier/management/commands/__init__.py
magic_notifier/management/commands/connect_telegram.py
magic_notifier/management/commands/test_email_template.py
magic_notifier/migrations/0001_initial.py
magic_notifier/migrations/0002_notification_expires_notification_is_encrypted_and_more.py
magic_notifier/migrations/0003_notification_inited_by.py
magic_notifier/migrations/__init__.py
magic_notifier/push_clients/__init__.py
magic_notifier/push_clients/expo.py
magic_notifier/push_clients/fcm.py
magic_notifier/sms_clients/__init__.py
magic_notifier/sms_clients/base.py
magic_notifier/sms_clients/cgsms_client.py
magic_notifier/sms_clients/nexa_client.py
magic_notifier/sms_clients/twilio_client.py
magic_notifier/telegram_clients/__init__.py
magic_notifier/telegram_clients/telethon.py
magic_notifier/templates/base_notifier/email.html
magic_notifier/templates/base_notifier/email.txt
magic_notifier/templates/base_notifier/push.json
magic_notifier/templates/base_notifier/sms.txt
magic_notifier/whatsapp_clients/__init__.py
magic_notifier/whatsapp_clients/waha_client.py
django_magic_notifier-0.4.0.dist-info/LICENSE
django_magic_notifier-0.4.0.dist-info/METADATA
django_magic_notifier-0.4.0.dist-info/WHEEL
django_magic_notifier-0.4.0.dist-info/top_level.txt
django_magic_notifier-0.4.0.dist-info/RECORD
