Metadata-Version: 2.1
Name: django-magic-notifier
Version: 0.4.0
Summary: A notifications library for Djangonauts that support email, sms and push.
Home-page: https://github.com/jefcolbi/django-magic-notifier
Author: jefcolbi
Author-email: jefcolbi@gmail.com
License: MIT
Classifier: Natural Language :: English
Classifier: Natural Language :: French
Classifier: Development Status :: 5 - Production/Stable
Classifier: Programming Language :: Python
Classifier: Programming Language :: Python :: 3.6
Classifier: Programming Language :: Python :: 3.7
Classifier: Programming Language :: Python :: 3.8
Classifier: Programming Language :: Python :: 3.9
Classifier: Programming Language :: Python :: 3.10
Classifier: Programming Language :: Python :: 3.11
Classifier: Programming Language :: Python :: 3.12
Classifier: Programming Language :: Python :: 3.13
Classifier: Framework :: Django :: 2.2
Classifier: Framework :: Django :: 3.0
Classifier: Framework :: Django :: 3.1
Classifier: Framework :: Django :: 3.2
Classifier: Framework :: Django :: 4.0
Classifier: Framework :: Django :: 4.1
Classifier: Framework :: Django :: 4.2
Classifier: License :: OSI Approved :: GNU General Public License v3 or later (GPLv3+)
Requires-Python: >=3.6.0
License-File: LICENSE
Requires-Dist: django>=2.2
Requires-Dist: djangorestframework
Requires-Dist: requests
Requires-Dist: mjml-python
Provides-Extra: amazon_ses
Requires-Dist: django-ses; extra == "amazon-ses"
Provides-Extra: fcm
Requires-Dist: pyfcm; extra == "fcm"
Provides-Extra: push
Requires-Dist: channels; extra == "push"
Requires-Dist: channels-redis; extra == "push"
Provides-Extra: telegram
Requires-Dist: telethon; extra == "telegram"
Provides-Extra: twilio
Requires-Dist: twilio; extra == "twilio"
